dj_polyglot/__init__.py
dj_polyglot/management/__init__.py
dj_polyglot/management/commands/__init__.py
dj_polyglot/management/commands/djp_pull_translations.py
dj_polyglot/management/commands/djp_push_translations.py
dj_polyglot/management/commands/pull_translations.py
dj_polyglot/management/commands/push_translations.py
dj_polyglot-0.20.0.dist-info/METADATA
dj_polyglot-0.20.0.dist-info/WHEEL
dj_polyglot-0.20.0.dist-info/top_level.txt
dj_polyglot-0.20.0.dist-info/RECORD
