Metadata-Version: 2.1
Name: dj-polyglot
Version: 0.20.0
Home-page: https://github.com/Thutmose3/dj-polyglot-lib
Classifier: Framework :: Django
Classifier: Programming Language :: Python
Requires-Dist: Django>=3.2
Requires-Dist: polib>=1.2.0
